{
  "slug": "median-of-two-sorted-arrays",
  "title": "两个有序数组的中位数",
  "difficulty": "HARD",
  "tags": [
    "二分查找",
    "数组"
  ],
  "content": "给定两个按非降序排列的整数数组 nums1 和 nums2，长度分别为 m 和 n，要求在不实际合并的前提下求出将二者整体排序后序列的中位数。若总长度为奇数，中位数为中间元素；若为偶数，则为中间两元素平均值，结果可能为小数（.5）。任一数组可以为空，总长度至少为 1，需要正确处理重复值与极端长度差异的情况。",
  "input_description": "第一行输入整数 m，第二行输入 m 个按非降序排列的整数表示 nums1；第三行输入整数 n，第四行输入 n 个按非降序排列的整数表示 nums2。若某个数组长度为 0，则对应的下一行可以为空行。",
  "output_description": "输出一个数，为合并有序序列的中位数。若为整数直接输出整数形式，若为小数输出一位小数（形如 2.5），行尾换行。",
  "constraints": "$0 \\le m,n \\le 10^{5}$，$m+n \\ge 1$，元素绝对值不超过 $10^{9}$。",
  "is_spj": false,
  "spj_code": null,
  "testcases": [
    {
      "input_text": "2\n1 3\n2\n2 4\n",
      "output_text": "2.5\n",
      "is_sample": true
    },
    {
      "input_text": "1\n1\n1\n2\n",
      "output_text": "1.5\n",
      "is_sample": true
    },
    {
      "input_text": "0\n\n1\n5\n",
      "output_text": "5\n",
      "is_sample": false
    },
    {
      "input_text": "3\n1 2 3\n0\n\n",
      "output_text": "2\n",
      "is_sample": false
    },
    {
      "input_text": "4\n1 3 8 9\n4\n7 11 18 19\n",
      "output_text": "8.5\n",
      "is_sample": false
    },
    {
      "input_text": "2\n1 2\n2\n3 4\n",
      "output_text": "2.5\n",
      "is_sample": false
    },
    {
      "input_text": "2\n1 2\n1\n3\n",
      "output_text": "2\n",
      "is_sample": false
    },
    {
      "input_text": "2\n0 0\n2\n0 0\n",
      "output_text": "0\n",
      "is_sample": false
    },
    {
      "input_text": "1\n1\n1\n1\n",
      "output_text": "1\n",
      "is_sample": false
    },
    {
      "input_text": "1\n2\n5\n1 3 4 5 6\n",
      "output_text": "3\n",
      "is_sample": false
    },
    {
      "input_text": "4\n1 2 3 4\n4\n5 6 7 8\n",
      "output_text": "4.5\n",
      "is_sample": false
    },
    {
      "input_text": "1\n1000000\n2\n1000001 1000002\n",
      "output_text": "1000001\n",
      "is_sample": false
    },
    {
      "input_text": "3\n-5 -3 -1\n3\n1 3 5\n",
      "output_text": "0\n",
      "is_sample": false
    },
    {
      "input_text": "4\n1 2 2 2\n5\n2 2 2 2 2\n",
      "output_text": "2\n",
      "is_sample": false
    },
    {
      "input_text": "0\n\n0\n\n",
      "output_text": "0\n",
      "is_sample": false
    },
    {
      "input_text": "1\n0\n0\n\n",
      "output_text": "0\n",
      "is_sample": false
    },
    {
      "input_text": "0\n\n1\n0\n",
      "output_text": "0\n",
      "is_sample": false
    },
    {
      "input_text": "3\n1 4 7\n5\n2 3 6 8 9\n",
      "output_text": "4.5\n",
      "is_sample": false
    },
    {
      "input_text": "3\n10 20 30\n5\n5 15 25 35 45\n",
      "output_text": "22.5\n",
      "is_sample": false
    },
    {
      "input_text": "5\n1 2 3 4 5\n1\n6\n",
      "output_text": "3.5\n",
      "is_sample": false
    }
  ]
}
